SurveyHumpbackWhale.py
SurveyHumpbackWhale-2020.1.0.dist-info/METADATA
SurveyHumpbackWhale-2020.1.0.dist-info/WHEEL
SurveyHumpbackWhale-2020.1.0.dist-info/top_level.txt
SurveyHumpbackWhale-2020.1.0.dist-info/RECORD
