Metadata-Version: 2.1
Name: SurveyHumpbackWhale
Version: 2020.1.0
Summary: Survey utils module to make transforms and proccess this sources of data easily
Home-page: UNKNOWN
Author: UNKNOWN
Author-email: UNKNOWN
License: UNKNOWN
Platform: UNKNOWN
